ethernity_cloud_runner_py/__init__.py
ethernity_cloud_runner_py/crypto.py
ethernity_cloud_runner_py/enums.py
ethernity_cloud_runner_py/ipfs.py
ethernity_cloud_runner_py/runner.py
ethernity_cloud_runner_py/utils.py
ethernity_cloud_runner_py/contract/__init__.py
ethernity_cloud_runner_py/contract/abi/__init__.py
ethernity_cloud_runner_py/contract/abi/bloxbergAbi.py
ethernity_cloud_runner_py/contract/abi/imageRegistryAbi.py
ethernity_cloud_runner_py/contract/abi/polygonAbi.py
ethernity_cloud_runner_py/contract/operation/__init__.py
ethernity_cloud_runner_py/contract/operation/bloxbergProtocolContract.py
ethernity_cloud_runner_py/contract/operation/imageRegistryContract.py
ethernity_cloud_runner_py/contract/operation/polygonProtocolContract.py
ethernity_cloud_runner-0.0.14.dist-info/LICENSE
ethernity_cloud_runner-0.0.14.dist-info/METADATA
ethernity_cloud_runner-0.0.14.dist-info/WHEEL
ethernity_cloud_runner-0.0.14.dist-info/top_level.txt
ethernity_cloud_runner-0.0.14.dist-info/RECORD
